bcryptor
