Metadata-Version: 1.0
Name: Bcryptor
Version: 1.2.2
Summary: Python wrapper for bcrypt
Home-page: http://www.bitbucket.org/ares/bcryptor/
Author: Jonas Melian
Author-email: jonas@mailup.net
License: UNKNOWN
Keywords: bcrypt,crypto,cryptography,hash,openbsd,password,security
Platform: UNKNOWN
Classifier: Development Status :: 5 - Production/Stable
Classifier: Environment :: Web Environment
Classifier: Environment :: Other Environment
Classifier: Intended Audience :: Developers
Classifier: License :: OSI Approved :: ISC License (ISCL)
Classifier: Operating System :: POSIX
Classifier: Operating System :: POSIX :: Linux
Classifier: Programming Language :: C
Classifier: Programming Language :: Python :: 2.4
Classifier: Topic :: Security :: Cryptography
